extension_changer/__init__.py
extension_changer/__main__.py
extension_changer/extension_changer.py
extension_changer/resources/__init__.py
extension_changer/resources/icon.icns
extension_changer/resources/icon.ico
extension_changer/resources/icon.png
extension_changer-1.0.1.dist-info/licenses/LICENSE
extension_changer-1.0.1.dist-info/METADATA
extension_changer-1.0.1.dist-info/WHEEL
extension_changer-1.0.1.dist-info/entry_points.txt
extension_changer-1.0.1.dist-info/top_level.txt
extension_changer-1.0.1.dist-info/RECORD
