Metadata-Version: 2.4
Name: extension_changer
Version: 1.0.1
Summary: A cross-platform utility for batch changing file extensions
Author-email: Naveen Vasudevan <naveenovan@gmail.com>
License-Expression: MIT
Project-URL: Homepage, https://github.com/kuroonai/exchange
Project-URL: Issues, https://github.com/kuroonai/exchange/issues
Project-URL: Documentation, https://github.com/kuroonai/exchange#readme
Keywords: file,extension,batch,converter,utility
Classifier: Development Status :: 4 - Beta
Classifier: Intended Audience :: End Users/Desktop
Classifier: Programming Language :: Python :: 3
Classifier: Programming Language :: Python :: 3.7
Classifier: Programming Language :: Python :: 3.8
Classifier: Programming Language :: Python :: 3.9
Classifier: Programming Language :: Python :: 3.10
Classifier: Programming Language :: Python :: 3.11
Classifier: Topic :: Utilities
Classifier: Topic :: Desktop Environment :: File Managers
Requires-Python: >=3.7
License-File: LICENSE
Requires-Dist: PySide6>=6.0.0
Dynamic: license-file
